<?xml version="1.0" encoding="UTF-8"?>
<objects serializationModel="Studio.02.00.00">
	<object class="AudioFile" id="{dd44f34b-b120-4c21-a2b7-91f6218a5031}">
		<property name="assetPath">
			<value>footstep4.wav</value>
		</property>
		<property name="frequencyInKHz">
			<value>44.0999985</value>
		</property>
		<property name="channelCount">
			<value>1</value>
		</property>
		<property name="length">
			<value>0.12301587301587301</value>
		</property>
		<relationship name="masterAssetFolder">
			<destination>{dc0ae609-3da7-40e6-acba-b19451f17f45}</destination>
		</relationship>
	</object>
</objects>
